codex_of_the_damned/__init__.py
codex_of_the_damned/__main__.py
codex_of_the_damned/config.py
codex_of_the_damned/navigation.py
codex_of_the_damned/static/css/base.css
codex_of_the_damned/static/fonts/fa-brands-400.eot
codex_of_the_damned/static/fonts/fa-brands-400.svg
codex_of_the_damned/static/fonts/fa-brands-400.ttf
codex_of_the_damned/static/fonts/fa-brands-400.woff
codex_of_the_damned/static/fonts/fa-brands-400.woff2
codex_of_the_damned/static/fonts/fa-solid-900.eot
codex_of_the_damned/static/fonts/fa-solid-900.svg
codex_of_the_damned/static/fonts/fa-solid-900.ttf
codex_of_the_damned/static/fonts/fa-solid-900.woff
codex_of_the_damned/static/fonts/fa-solid-900.woff2
codex_of_the_damned/static/img/25th-anniversary.webp
codex_of_the_damned/static/img/30th-anniversary.webp
codex_of_the_damned/static/img/anarchs-unbound.webp
codex_of_the_damned/static/img/anthology-1.webp
codex_of_the_damned/static/img/background.jpg
codex_of_the_damned/static/img/blood.svg
codex_of_the_damned/static/img/codex.jpg
codex_of_the_damned/static/img/dark-pack.png
codex_of_the_damned/static/img/echoes-of-gehenna.webp
codex_of_the_damned/static/img/fall-of-london.webp
codex_of_the_damned/static/img/favicon.ico
codex_of_the_damned/static/img/fifth-edition.webp
codex_of_the_damned/static/img/first-blood.webp
codex_of_the_damned/static/img/jol-interface.jpg
codex_of_the_damned/static/img/kickstarter.webp
codex_of_the_damned/static/img/kot.webp
codex_of_the_damned/static/img/krzystof-karski.png
codex_of_the_damned/static/img/lackeyccg-chat-macros.png
codex_of_the_damned/static/img/lackeyccg-deck-browse.png
codex_of_the_damned/static/img/lackeyccg-download-card-images.png
codex_of_the_damned/static/img/lackeyccg-host-game-ip.png
codex_of_the_damned/static/img/lackeyccg-interface.png
codex_of_the_damned/static/img/lackeyccg-plugin-download.png
codex_of_the_damned/static/img/lackeyccg-plugin-install.png
codex_of_the_damned/static/img/lackeyccg-profile.png
codex_of_the_damned-1.93.dist-info/METADATA
codex_of_the_damned-1.93.dist-info/WHEEL
codex_of_the_damned-1.93.dist-info/entry_points.txt
codex_of_the_damned-1.93.dist-info/top_level.txt
codex_of_the_damned-1.93.dist-info/RECORD
