Metadata-Version: 2.2
Name: codex-of-the-damned
Version: 1.93
Summary: Website on VTES Strategy, cards rulings and TWD search interface
Author-email: Lionel Panhaleux <lionel.panhaleux+codex@gmail.com>
Project-URL: Homepage, https://codex-of-the-damned.org
Project-URL: Repository, https://github.com/lionel-panhaleux/codex-of-the-damned
Keywords: vtes,Vampire: The Eternal Struggle,CCG,TWD,TWDA
Classifier: Programming Language :: Python :: 3.11
Classifier: Programming Language :: Python :: 3.12
Classifier: Programming Language :: Python :: 3.13
Classifier: License :: OSI Approved :: MIT License
Classifier: Development Status :: 5 - Production/Stable
Classifier: Natural Language :: English
Classifier: Operating System :: OS Independent
Classifier: Framework :: Flask
Classifier: Topic :: Internet :: WWW/HTTP :: WSGI :: Application
Requires-Python: >=3.11
Requires-Dist: flask>=3
Requires-Dist: flask-babel>=4
Requires-Dist: unidecode>=1
Requires-Dist: Jinja2>=3
Provides-Extra: dev
Requires-Dist: black>=24; extra == "dev"
Requires-Dist: build>=1; extra == "dev"
Requires-Dist: check-manifest>=0; extra == "dev"
Requires-Dist: ipython>=8; extra == "dev"
Requires-Dist: pytest>=8; extra == "dev"
Requires-Dist: requests>=2; extra == "dev"
Requires-Dist: ruff>=0; extra == "dev"
Requires-Dist: setuptools_scm>=8; extra == "dev"
Requires-Dist: twine>=5; extra == "dev"
